sws_py_sdk/__init__.py
sws_py_sdk/cloudlib.py
sws_py_sdk/ecom.py
sws_py_sdk/firewall_header.py
sws_py_sdk/identity.py
sws_py_sdk/license.py
sws_py_sdk/service.py
sws_py_sdk/sws.py
sws_py_sdk/sws_client.py
sws_py_sdk-0.10.5.dist-info/METADATA
sws_py_sdk-0.10.5.dist-info/WHEEL
sws_py_sdk-0.10.5.dist-info/top_level.txt
sws_py_sdk-0.10.5.dist-info/RECORD
